dotdata/__init__.py
dotdata/core/__init__.py
dotdata-0.0.1.dist-info/METADATA
dotdata-0.0.1.dist-info/WHEEL
dotdata-0.0.1.dist-info/top_level.txt
dotdata-0.0.1.dist-info/RECORD
