Metadata-Version: 2.1
Name: dotdata
Version: 0.0.1
Summary: dotData package
Home-page: https://dotdata.com/
Author: dotData, Inc.
Author-email: info@dotdata.com
License: UNKNOWN
Platform: UNKNOWN
Classifier: Programming Language :: Python :: 3
Requires-Python: >=3.6
